{"adult": false, "backdrop_path": "/lWf1aiqDZqUbhrw8DnsfV8Ql7CP.jpg", "genre_ids": [10751, 16, 35, 12], "id": 777350, "original_language": "en", "original_title": "Dory's Reef Cam", "overview": "Dive into the waters below and watch the aquatic wildlife from the world of Nemo and Dory.", "popularity": 164.309, "poster_path": "/mMWLGu9pFymqipN8yvISHsAaj72.jpg", "release_date": "2020-12-18", "title": "Dory's Reef Cam", "video": true, "vote_average": 6, "vote_count": 106, "poster_location": "d:\\oop_project\\posters\\CAM.jpg", "data_location": "D:\\oop_project\\movies\\CAM.mkv"}